UserReadWriteMemory/__init__.py
UserReadWriteMemory-1.2.1.dist-info/METADATA
UserReadWriteMemory-1.2.1.dist-info/WHEEL
UserReadWriteMemory-1.2.1.dist-info/top_level.txt
UserReadWriteMemory-1.2.1.dist-info/RECORD
