Metadata-Version: 2.1
Name: UserReadWriteMemory
Version: 1.2.1
Summary: Reading and writing to the memory of any process.
Home-page: https://github.com/User00092/UserReadWriteMemory/tree/1.2.1
Author: User0092
Author-email: unknownuser0092@protonmail.com
License: MIT
Keywords: Read Memory,Write Memory,Process memory,Hacking,UserReadWriteMemory
Classifier: Development Status :: 5 - Production/Stable
Classifier: Topic :: Utilities
Classifier: Operating System :: MacOS :: MacOS X
Classifier: Operating System :: Microsoft :: Windows
Classifier: Operating System :: POSIX :: Linux
Classifier: Programming Language :: Python
Classifier: Intended Audience :: Developers
Requires-Python: >=3.4.0
